{"name":"Dataspin Analytics SDK for Unity3D","tagline":"Dataspin is an all-in-one back-end solution to manage your game and help you earn more.","body":"## Welcome to Dataspin Analytics SDK for Unity3D page\r\n\r\nDataspin is an all-in-one back-end solution to manage your game and help you earn more. Tailored for gaming. Lets you communicate with your players better, reward the whales, incentivize, engage, retain. Segment, target them with campaigns, offer items and promos. Manage your store efficiently.\r\n\r\n### Easy Unity3D integration\r\nSimply import `.unitypackage`, drop prefab into scene and fire following functions.\r\n```\r\nDataspin.Instance.RegisterUser(\"John\", \"Dataspin\", \"john@Dataspin.io\");\r\nDataspin.Instance.RegisterDevice(<notification_id>);\r\nDataspin.Instance.StartSession();\r\n```\r\n\r\n### End-to-end solution\r\nAnalytics. Player segmentation. Campaigns. Predictive analytics. All revenue sources. Player profiles. IAPs. Now all in one place.\r\n\r\n### Actionable Analytics\r\nReports, key metrics and predictions. And the tools to put them to work.\r\n\r\n### Support or Contact\r\nHaving trouble with SDK? Check out the documentation at https://github.com/Dataspin/Dataspin_2.0-Unity-Plugin/wiki or contact rafal@dataspin.io and we’ll help you sort it out.\r\n\r\n### Cutting-Edge Tech\r\nIndustry-grade back-end. Based on the superfast and powerful SAP HANA, used by Coca-Cola or Samsung among others.","google":"","note":"Don't delete this file! It's used internally to help with page regeneration."}